farmsks/__init__.py
farmsks/functions.py
farmsks-0.1.3.dist-info/METADATA
farmsks-0.1.3.dist-info/WHEEL
farmsks-0.1.3.dist-info/licenses/LICENSE.txt
farmsks-0.1.3.dist-info/RECORD
