Metadata-Version: 2.4
Name: farmsks
Version: 0.1.3
Summary: Useful defs
Author-email: Samyar Sameni <samyar4@gmail.com>
License-File: LICENSE.txt
Classifier: License :: OSI Approved :: MIT License
Classifier: Operating System :: OS Independent
Classifier: Programming Language :: Python :: 3
Requires-Python: >=3.0
